sentry_extension/__init__.py
sentry_extension/constants.py
sentry_extension/utils.py
ipython_sentry_extension-0.0.1.dist-info/METADATA
ipython_sentry_extension-0.0.1.dist-info/WHEEL
ipython_sentry_extension-0.0.1.dist-info/RECORD
