Metadata-Version: 2.1
Name: ipython_sentry_extension
Version: 0.0.1
Author-email: Pavel Komar <pvkomar@cloud.ru>
Keywords: Extension,Jupyter
Classifier: Programming Language :: Python
Classifier: Programming Language :: Python :: 3
Classifier: Programming Language :: Python :: 3.8
Classifier: Programming Language :: Python :: 3.9
Classifier: Programming Language :: Python :: 3.10
Classifier: Programming Language :: Python :: 3.11
Requires-Python: >=3.8
Requires-Dist: ipython>=7.0.0
Requires-Dist: sentry-sdk>=1.5.5
